polarbears/__init__.py
polarbears/dataframe/__init__.py
polarbears/error.py
polarbears-0.0.0.dist-info/WHEEL
polarbears-0.0.0.dist-info/METADATA
polarbears-0.0.0.dist-info/RECORD
