Metadata-Version: 2.1
Name: polarbears
Version: 0.0.0
Summary: 
License: MIT
Author: Chris Pryer
Requires-Python: >=3.9,<4.0
Classifier: License :: OSI Approved :: MIT License
Classifier: Programming Language :: Python :: 3
Classifier: Programming Language :: Python :: 3.10
Classifier: Programming Language :: Python :: 3.9
Requires-Dist: polars (>=0.13.16,<0.14.0)
